[
  {
    "description": "all fields empty",
    "companyNumber": "",
    "mobileNumber": "",
    "password": ""
  },
  {
    "description": "company number empty",
    "companyNumber": "",
    "mobileNumber": "510203012",
    "password": "Aa#1234567"
  },
  {
    "description": "mobile number empty",
    "companyNumber": "F2147",
    "mobileNumber": "",
    "password": "Aa#1234567"
  },
  {
    "description": "password empty",
    "companyNumber": "F2147",
    "mobileNumber": "510203012",
    "password": ""
  }
]
